{"frames": [

{
	"filename": "06-b-01.png",
	"frame": {"x":670,"y":762,"w":195,"h":207},
	"rotated": false,
	"trimmed": true,
	"spriteSourceSize": {"x":146,"y":96,"w":195,"h":207},
	"sourceSize": {"w":485,"h":368}
},
{
	"filename": "06-n-01.png",
	"frame": {"x":423,"y":803,"w":195,"h":190},
	"rotated": false,
	"trimmed": true,
	"spriteSourceSize": {"x":146,"y":104,"w":195,"h":190},
	"sourceSize": {"w":485,"h":368}
},
{
	"filename": "06-n-02.png",
	"frame": {"x":1,"y":1152,"w":182,"h":190},
	"rotated": false,
	"trimmed": true,
	"spriteSourceSize": {"x":146,"y":104,"w":182,"h":190},
	"sourceSize": {"w":485,"h":368}
},
{
	"filename": "06-n-03.png",
	"frame": {"x":185,"y":1175,"w":174,"h":189},
	"rotated": false,
	"trimmed": true,
	"spriteSourceSize": {"x":146,"y":105,"w":174,"h":189},
	"sourceSize": {"w":485,"h":368}
},
{
	"filename": "06-n-04.png",
	"frame": {"x":800,"y":971,"w":173,"h":189},
	"rotated": false,
	"trimmed": true,
	"spriteSourceSize": {"x":147,"y":105,"w":173,"h":189},
	"sourceSize": {"w":485,"h":368}
},
{
	"filename": "06-n-05.png",
	"frame": {"x":800,"y":1162,"w":173,"h":188},
	"rotated": false,
	"trimmed": true,
	"spriteSourceSize": {"x":147,"y":106,"w":173,"h":188},
	"sourceSize": {"w":485,"h":368}
},
{
	"filename": "06-n-06.png",
	"frame": {"x":580,"y":1163,"w":173,"h":187},
	"rotated": false,
	"trimmed": true,
	"spriteSourceSize": {"x":147,"y":107,"w":173,"h":187},
	"sourceSize": {"w":485,"h":368}
},
{
	"filename": "06-n-07.png",
	"frame": {"x":361,"y":1186,"w":172,"h":187},
	"rotated": false,
	"trimmed": true,
	"spriteSourceSize": {"x":148,"y":107,"w":172,"h":187},
	"sourceSize": {"w":485,"h":368}
},
{
	"filename": "06-n-08.png",
	"frame": {"x":177,"y":1366,"w":172,"h":186},
	"rotated": false,
	"trimmed": true,
	"spriteSourceSize": {"x":148,"y":108,"w":172,"h":186},
	"sourceSize": {"w":485,"h":368}
},
{
	"filename": "06-n-09.png",
	"frame": {"x":1,"y":1535,"w":172,"h":186},
	"rotated": false,
	"trimmed": true,
	"spriteSourceSize": {"x":148,"y":108,"w":172,"h":186},
	"sourceSize": {"w":485,"h":368}
},
{
	"filename": "06-n-10.png",
	"frame": {"x":831,"y":193,"w":187,"h":187},
	"rotated": false,
	"trimmed": true,
	"spriteSourceSize": {"x":148,"y":107,"w":187,"h":187},
	"sourceSize": {"w":485,"h":368}
},
{
	"filename": "06-n-11.png",
	"frame": {"x":218,"y":794,"w":203,"h":187},
	"rotated": false,
	"trimmed": true,
	"spriteSourceSize": {"x":147,"y":107,"w":203,"h":187},
	"sourceSize": {"w":485,"h":368}
},
{
	"filename": "06-n-12.png",
	"frame": {"x":1,"y":772,"w":215,"h":188},
	"rotated": false,
	"trimmed": true,
	"spriteSourceSize": {"x":147,"y":106,"w":215,"h":188},
	"sourceSize": {"w":485,"h":368}
},
{
	"filename": "06-n-13.png",
	"frame": {"x":503,"y":420,"w":215,"h":189},
	"rotated": false,
	"trimmed": true,
	"spriteSourceSize": {"x":147,"y":105,"w":215,"h":189},
	"sourceSize": {"w":485,"h":368}
},
{
	"filename": "06-n-14.png",
	"frame": {"x":244,"y":603,"w":215,"h":189},
	"rotated": false,
	"trimmed": true,
	"spriteSourceSize": {"x":147,"y":105,"w":215,"h":189},
	"sourceSize": {"w":485,"h":368}
},
{
	"filename": "06-n-15.png",
	"frame": {"x":720,"y":571,"w":214,"h":189},
	"rotated": false,
	"trimmed": true,
	"spriteSourceSize": {"x":146,"y":105,"w":214,"h":189},
	"sourceSize": {"w":485,"h":368}
},
{
	"filename": "06-n-16.png",
	"frame": {"x":461,"y":611,"w":207,"h":190},
	"rotated": false,
	"trimmed": true,
	"spriteSourceSize": {"x":146,"y":104,"w":207,"h":190},
	"sourceSize": {"w":485,"h":368}
},
{
	"filename": "06-w-01.png",
	"frame": {"x":204,"y":983,"w":195,"h":190},
	"rotated": false,
	"trimmed": true,
	"spriteSourceSize": {"x":146,"y":104,"w":195,"h":190},
	"sourceSize": {"w":485,"h":368}
},
{
	"filename": "06-w-02.png",
	"frame": {"x":1,"y":192,"w":255,"h":190},
	"rotated": false,
	"trimmed": true,
	"spriteSourceSize": {"x":146,"y":104,"w":255,"h":190},
	"sourceSize": {"w":485,"h":368}
},
{
	"filename": "06-w-03.png",
	"frame": {"x":254,"y":402,"w":247,"h":199},
	"rotated": false,
	"trimmed": true,
	"spriteSourceSize": {"x":146,"y":104,"w":247,"h":199},
	"sourceSize": {"w":485,"h":368}
},
{
	"filename": "06-w-04.png",
	"frame": {"x":1,"y":573,"w":241,"h":197},
	"rotated": false,
	"trimmed": true,
	"spriteSourceSize": {"x":143,"y":102,"w":241,"h":197},
	"sourceSize": {"w":485,"h":368}
},
{
	"filename": "06-w-05.png",
	"frame": {"x":539,"y":214,"w":250,"h":204},
	"rotated": false,
	"trimmed": true,
	"spriteSourceSize": {"x":139,"y":98,"w":250,"h":204},
	"sourceSize": {"w":485,"h":368}
},
{
	"filename": "06-w-06.png",
	"frame": {"x":279,"y":190,"w":258,"h":210},
	"rotated": false,
	"trimmed": true,
	"spriteSourceSize": {"x":135,"y":95,"w":258,"h":210},
	"sourceSize": {"w":485,"h":368}
},
{
	"filename": "06-w-07.png",
	"frame": {"x":556,"y":1,"w":273,"h":211},
	"rotated": false,
	"trimmed": true,
	"spriteSourceSize": {"x":140,"y":99,"w":273,"h":211},
	"sourceSize": {"w":485,"h":368}
},
{
	"filename": "06-w-08.png",
	"frame": {"x":1,"y":1,"w":276,"h":189},
	"rotated": false,
	"trimmed": true,
	"spriteSourceSize": {"x":144,"y":103,"w":276,"h":189},
	"sourceSize": {"w":485,"h":368}
},
{
	"filename": "06-w-09.png",
	"frame": {"x":279,"y":1,"w":275,"h":187},
	"rotated": false,
	"trimmed": true,
	"spriteSourceSize": {"x":148,"y":106,"w":275,"h":187},
	"sourceSize": {"w":485,"h":368}
},
{
	"filename": "06-w-10.png",
	"frame": {"x":1,"y":384,"w":251,"h":187},
	"rotated": false,
	"trimmed": true,
	"spriteSourceSize": {"x":149,"y":106,"w":251,"h":187},
	"sourceSize": {"w":485,"h":368}
},
{
	"filename": "06-w-11.png",
	"frame": {"x":791,"y":382,"w":219,"h":187},
	"rotated": false,
	"trimmed": true,
	"spriteSourceSize": {"x":151,"y":105,"w":219,"h":187},
	"sourceSize": {"w":485,"h":368}
},
{
	"filename": "06-w-12.png",
	"frame": {"x":1,"y":962,"w":201,"h":188},
	"rotated": false,
	"trimmed": true,
	"spriteSourceSize": {"x":149,"y":104,"w":201,"h":188},
	"sourceSize": {"w":485,"h":368}
},
{
	"filename": "06-w-13.png",
	"frame": {"x":401,"y":995,"w":177,"h":189},
	"rotated": false,
	"trimmed": true,
	"spriteSourceSize": {"x":147,"y":103,"w":177,"h":189},
	"sourceSize": {"w":485,"h":368}
},
{
	"filename": "06-w-14.png",
	"frame": {"x":1,"y":1344,"w":174,"h":189},
	"rotated": false,
	"trimmed": true,
	"spriteSourceSize": {"x":146,"y":103,"w":174,"h":189},
	"sourceSize": {"w":485,"h":368}
},
{
	"filename": "06-w-15.png",
	"frame": {"x":620,"y":971,"w":178,"h":190},
	"rotated": false,
	"trimmed": true,
	"spriteSourceSize": {"x":146,"y":103,"w":178,"h":190},
	"sourceSize": {"w":485,"h":368}
},
{
	"filename": "06-w-16.png",
	"frame": {"x":831,"y":1,"w":188,"h":190},
	"rotated": false,
	"trimmed": true,
	"spriteSourceSize": {"x":146,"y":103,"w":188,"h":190},
	"sourceSize": {"w":485,"h":368}
}],
"meta": {
	"app": "http://www.codeandweb.com/texturepacker",
	"version": "1.0",
	"image": "06.png",
	"format": "RGBA8888",
	"size": {"w":1024,"h":2048},
	"scale": "1",
	"smartupdate": "$TexturePacker:SmartUpdate:3b363e9d691512042084682e6013283e:03838dfe89662a5aa4bcdd3f70af43fc:2e8c261208464067cbfcec86f0e04425$"
}
}
