{"frames": [

{
	"filename": "11-n-00.png",
	"frame": {"x":1,"y":1,"w":234,"h":224},
	"rotated": false,
	"trimmed": true,
	"spriteSourceSize": {"x":114,"y":95,"w":234,"h":224},
	"sourceSize": {"w":436,"h":388}
}],
"meta": {
	"app": "http://www.codeandweb.com/texturepacker",
	"version": "1.0",
	"image": "11.png",
	"format": "RGBA8888",
	"size": {"w":256,"h":256},
	"scale": "1",
	"smartupdate": "$TexturePacker:SmartUpdate:71326cdfffb928cb966fb0da267ae065:47a3c91850789b4de241b6e52aebd549:aaee697773d245ec0ff66c8d6aa83826$"
}
}
