{"frames": [

{
	"filename": "02-b-00.png",
	"frame": {"x":636,"y":190,"w":193,"h":189},
	"rotated": false,
	"trimmed": true,
	"spriteSourceSize": {"x":805,"y":800,"w":193,"h":189},
	"sourceSize": {"w":1800,"h":1800}
},
{
	"filename": "02-n-00.png",
	"frame": {"x":624,"y":554,"w":194,"h":166},
	"rotated": false,
	"trimmed": true,
	"spriteSourceSize": {"x":804,"y":812,"w":194,"h":166},
	"sourceSize": {"w":1800,"h":1800}
},
{
	"filename": "02-n-01.png",
	"frame": {"x":215,"y":392,"w":192,"h":165},
	"rotated": false,
	"trimmed": true,
	"spriteSourceSize": {"x":805,"y":813,"w":192,"h":165},
	"sourceSize": {"w":1800,"h":1800}
},
{
	"filename": "02-n-02.png",
	"frame": {"x":195,"y":559,"w":190,"h":163},
	"rotated": false,
	"trimmed": true,
	"spriteSourceSize": {"x":806,"y":814,"w":190,"h":163},
	"sourceSize": {"w":1800,"h":1800}
},
{
	"filename": "02-n-03.png",
	"frame": {"x":1,"y":724,"w":189,"h":162},
	"rotated": false,
	"trimmed": true,
	"spriteSourceSize": {"x":807,"y":815,"w":189,"h":162},
	"sourceSize": {"w":1800,"h":1800}
},
{
	"filename": "02-n-04.png",
	"frame": {"x":536,"y":901,"w":188,"h":160},
	"rotated": false,
	"trimmed": true,
	"spriteSourceSize": {"x":807,"y":816,"w":188,"h":160},
	"sourceSize": {"w":1800,"h":1800}
},
{
	"filename": "02-n-05.png",
	"frame": {"x":188,"y":888,"w":186,"h":158},
	"rotated": false,
	"trimmed": true,
	"spriteSourceSize": {"x":808,"y":817,"w":186,"h":158},
	"sourceSize": {"w":1800,"h":1800}
},
{
	"filename": "02-n-06.png",
	"frame": {"x":533,"y":1063,"w":184,"h":157},
	"rotated": false,
	"trimmed": true,
	"spriteSourceSize": {"x":809,"y":818,"w":184,"h":157},
	"sourceSize": {"w":1800,"h":1800}
},
{
	"filename": "02-n-07.png",
	"frame": {"x":186,"y":1208,"w":183,"h":155},
	"rotated": false,
	"trimmed": true,
	"spriteSourceSize": {"x":809,"y":819,"w":183,"h":155},
	"sourceSize": {"w":1800,"h":1800}
},
{
	"filename": "02-n-08.png",
	"frame": {"x":719,"y":1086,"w":181,"h":154},
	"rotated": false,
	"trimmed": true,
	"spriteSourceSize": {"x":810,"y":820,"w":181,"h":154},
	"sourceSize": {"w":1800,"h":1800}
},
{
	"filename": "02-n-09.png",
	"frame": {"x":1,"y":1368,"w":179,"h":152},
	"rotated": false,
	"trimmed": true,
	"spriteSourceSize": {"x":811,"y":821,"w":179,"h":152},
	"sourceSize": {"w":1800,"h":1800}
},
{
	"filename": "02-n-10.png",
	"frame": {"x":182,"y":1520,"w":176,"h":151},
	"rotated": false,
	"trimmed": true,
	"spriteSourceSize": {"x":812,"y":821,"w":176,"h":151},
	"sourceSize": {"w":1800,"h":1800}
},
{
	"filename": "02-n-11.png",
	"frame": {"x":507,"y":1534,"w":174,"h":149},
	"rotated": false,
	"trimmed": true,
	"spriteSourceSize": {"x":813,"y":822,"w":174,"h":149},
	"sourceSize": {"w":1800,"h":1800}
},
{
	"filename": "02-n-12.png",
	"frame": {"x":683,"y":1552,"w":172,"h":147},
	"rotated": false,
	"trimmed": true,
	"spriteSourceSize": {"x":814,"y":823,"w":172,"h":147},
	"sourceSize": {"w":1800,"h":1800}
},
{
	"filename": "02-n-13.png",
	"frame": {"x":176,"y":1823,"w":170,"h":146},
	"rotated": false,
	"trimmed": true,
	"spriteSourceSize": {"x":815,"y":824,"w":170,"h":146},
	"sourceSize": {"w":1800,"h":1800}
},
{
	"filename": "02-n-14.png",
	"frame": {"x":526,"y":1701,"w":168,"h":144},
	"rotated": false,
	"trimmed": true,
	"spriteSourceSize": {"x":816,"y":825,"w":168,"h":144},
	"sourceSize": {"w":1800,"h":1800}
},
{
	"filename": "02-n-15.png",
	"frame": {"x":687,"y":1847,"w":165,"h":142},
	"rotated": false,
	"trimmed": true,
	"spriteSourceSize": {"x":817,"y":826,"w":165,"h":142},
	"sourceSize": {"w":1800,"h":1800}
},
{
	"filename": "02-n-16.png",
	"frame": {"x":348,"y":1834,"w":167,"h":144},
	"rotated": false,
	"trimmed": true,
	"spriteSourceSize": {"x":816,"y":825,"w":167,"h":144},
	"sourceSize": {"w":1800,"h":1800}
},
{
	"filename": "02-n-17.png",
	"frame": {"x":1,"y":1824,"w":169,"h":145},
	"rotated": false,
	"trimmed": true,
	"spriteSourceSize": {"x":815,"y":824,"w":169,"h":145},
	"sourceSize": {"w":1800,"h":1800}
},
{
	"filename": "02-n-18.png",
	"frame": {"x":353,"y":1685,"w":171,"h":147},
	"rotated": false,
	"trimmed": true,
	"spriteSourceSize": {"x":814,"y":823,"w":171,"h":147},
	"sourceSize": {"w":1800,"h":1800}
},
{
	"filename": "02-n-19.png",
	"frame": {"x":179,"y":1673,"w":172,"h":148},
	"rotated": false,
	"trimmed": true,
	"spriteSourceSize": {"x":814,"y":822,"w":172,"h":148},
	"sourceSize": {"w":1800,"h":1800}
},
{
	"filename": "02-n-20.png",
	"frame": {"x":698,"y":1400,"w":174,"h":150},
	"rotated": false,
	"trimmed": true,
	"spriteSourceSize": {"x":813,"y":821,"w":174,"h":150},
	"sourceSize": {"w":1800,"h":1800}
},
{
	"filename": "02-n-21.png",
	"frame": {"x":1,"y":1522,"w":176,"h":151},
	"rotated": false,
	"trimmed": true,
	"spriteSourceSize": {"x":812,"y":820,"w":176,"h":151},
	"sourceSize": {"w":1800,"h":1800}
},
{
	"filename": "02-n-22.png",
	"frame": {"x":184,"y":1365,"w":178,"h":153},
	"rotated": false,
	"trimmed": true,
	"spriteSourceSize": {"x":811,"y":819,"w":178,"h":153},
	"sourceSize": {"w":1800,"h":1800}
},
{
	"filename": "02-n-23.png",
	"frame": {"x":528,"y":1222,"w":180,"h":154},
	"rotated": false,
	"trimmed": true,
	"spriteSourceSize": {"x":810,"y":818,"w":180,"h":154},
	"sourceSize": {"w":1800,"h":1800}
},
{
	"filename": "02-n-24.png",
	"frame": {"x":1,"y":1210,"w":181,"h":156},
	"rotated": false,
	"trimmed": true,
	"spriteSourceSize": {"x":810,"y":817,"w":181,"h":156},
	"sourceSize": {"w":1800,"h":1800}
},
{
	"filename": "02-n-25.png",
	"frame": {"x":188,"y":1048,"w":183,"h":158},
	"rotated": false,
	"trimmed": true,
	"spriteSourceSize": {"x":809,"y":816,"w":183,"h":158},
	"sourceSize": {"w":1800,"h":1800}
},
{
	"filename": "02-n-26.png",
	"frame": {"x":1,"y":888,"w":185,"h":160},
	"rotated": false,
	"trimmed": true,
	"spriteSourceSize": {"x":808,"y":815,"w":185,"h":160},
	"sourceSize": {"w":1800,"h":1800}
},
{
	"filename": "02-n-27.png",
	"frame": {"x":192,"y":724,"w":187,"h":162},
	"rotated": false,
	"trimmed": true,
	"spriteSourceSize": {"x":807,"y":814,"w":187,"h":162},
	"sourceSize": {"w":1800,"h":1800}
},
{
	"filename": "02-n-28.png",
	"frame": {"x":729,"y":760,"w":190,"h":162},
	"rotated": false,
	"trimmed": true,
	"spriteSourceSize": {"x":806,"y":814,"w":190,"h":162},
	"sourceSize": {"w":1800,"h":1800}
},
{
	"filename": "02-n-29.png",
	"frame": {"x":1,"y":558,"w":192,"h":164},
	"rotated": false,
	"trimmed": true,
	"spriteSourceSize": {"x":805,"y":813,"w":192,"h":164},
	"sourceSize": {"w":1800,"h":1800}
},
{
	"filename": "02-w-00.png",
	"frame": {"x":820,"y":592,"w":194,"h":166},
	"rotated": false,
	"trimmed": true,
	"spriteSourceSize": {"x":804,"y":812,"w":194,"h":166},
	"sourceSize": {"w":1800,"h":1800}
},
{
	"filename": "02-w-01.png",
	"frame": {"x":1,"y":1050,"w":183,"h":158},
	"rotated": false,
	"trimmed": true,
	"spriteSourceSize": {"x":809,"y":816,"w":183,"h":158},
	"sourceSize": {"w":1800,"h":1800}
},
{
	"filename": "02-w-02.png",
	"frame": {"x":522,"y":1378,"w":174,"h":154},
	"rotated": false,
	"trimmed": true,
	"spriteSourceSize": {"x":813,"y":820,"w":174,"h":154},
	"sourceSize": {"w":1800,"h":1800}
},
{
	"filename": "02-w-03.png",
	"frame": {"x":857,"y":1552,"w":163,"h":149},
	"rotated": false,
	"trimmed": true,
	"spriteSourceSize": {"x":818,"y":825,"w":163,"h":149},
	"sourceSize": {"w":1800,"h":1800}
},
{
	"filename": "02-w-04.png",
	"frame": {"x":373,"y":1105,"w":153,"h":145},
	"rotated": false,
	"trimmed": true,
	"spriteSourceSize": {"x":822,"y":830,"w":153,"h":145},
	"sourceSize": {"w":1800,"h":1800}
},
{
	"filename": "02-w-05.png",
	"frame": {"x":360,"y":1525,"w":145,"h":139},
	"rotated": false,
	"trimmed": true,
	"spriteSourceSize": {"x":826,"y":835,"w":145,"h":139},
	"sourceSize": {"w":1800,"h":1800}
},
{
	"filename": "02-w-06.png",
	"frame": {"x":371,"y":1252,"w":149,"h":136},
	"rotated": false,
	"trimmed": true,
	"spriteSourceSize": {"x":824,"y":832,"w":149,"h":136},
	"sourceSize": {"w":1800,"h":1800}
},
{
	"filename": "02-w-07.png",
	"frame": {"x":364,"y":1390,"w":156,"h":133},
	"rotated": false,
	"trimmed": true,
	"spriteSourceSize": {"x":821,"y":831,"w":156,"h":133},
	"sourceSize": {"w":1800,"h":1800}
},
{
	"filename": "02-w-08.png",
	"frame": {"x":696,"y":1703,"w":162,"h":138},
	"rotated": false,
	"trimmed": true,
	"spriteSourceSize": {"x":819,"y":829,"w":162,"h":138},
	"sourceSize": {"w":1800,"h":1800}
},
{
	"filename": "02-w-09.png",
	"frame": {"x":517,"y":1847,"w":168,"h":142},
	"rotated": false,
	"trimmed": true,
	"spriteSourceSize": {"x":816,"y":827,"w":168,"h":142},
	"sourceSize": {"w":1800,"h":1800}
},
{
	"filename": "02-w-10.png",
	"frame": {"x":1,"y":1675,"w":173,"h":147},
	"rotated": false,
	"trimmed": true,
	"spriteSourceSize": {"x":814,"y":825,"w":173,"h":147},
	"sourceSize": {"w":1800,"h":1800}
},
{
	"filename": "02-w-11.png",
	"frame": {"x":710,"y":1242,"w":173,"h":156},
	"rotated": false,
	"trimmed": true,
	"spriteSourceSize": {"x":810,"y":821,"w":173,"h":156},
	"sourceSize": {"w":1800,"h":1800}
},
{
	"filename": "02-w-12.png",
	"frame": {"x":376,"y":936,"w":155,"h":167},
	"rotated": false,
	"trimmed": true,
	"spriteSourceSize": {"x":806,"y":816,"w":155,"h":167},
	"sourceSize": {"w":1800,"h":1800}
},
{
	"filename": "02-w-13.png",
	"frame": {"x":381,"y":753,"w":153,"h":181},
	"rotated": false,
	"trimmed": true,
	"spriteSourceSize": {"x":803,"y":808,"w":153,"h":181},
	"sourceSize": {"w":1800,"h":1800}
},
{
	"filename": "02-w-14.png",
	"frame": {"x":387,"y":563,"w":164,"h":188},
	"rotated": false,
	"trimmed": true,
	"spriteSourceSize": {"x":799,"y":805,"w":164,"h":188},
	"sourceSize": {"w":1800,"h":1800}
},
{
	"filename": "02-w-15.png",
	"frame": {"x":553,"y":722,"w":174,"h":177},
	"rotated": false,
	"trimmed": true,
	"spriteSourceSize": {"x":793,"y":820,"w":174,"h":177},
	"sourceSize": {"w":1800,"h":1800}
},
{
	"filename": "02-w-16.png",
	"frame": {"x":726,"y":924,"w":187,"h":160},
	"rotated": false,
	"trimmed": true,
	"spriteSourceSize": {"x":787,"y":841,"w":187,"h":160},
	"sourceSize": {"w":1800,"h":1800}
},
{
	"filename": "02-w-17.png",
	"frame": {"x":630,"y":381,"w":198,"h":171},
	"rotated": false,
	"trimmed": true,
	"spriteSourceSize": {"x":780,"y":834,"w":198,"h":171},
	"sourceSize": {"w":1800,"h":1800}
},
{
	"filename": "02-w-18.png",
	"frame": {"x":831,"y":212,"w":189,"h":181},
	"rotated": false,
	"trimmed": true,
	"spriteSourceSize": {"x":794,"y":829,"w":189,"h":181},
	"sourceSize": {"w":1800,"h":1800}
},
{
	"filename": "02-w-19.png",
	"frame": {"x":830,"y":395,"w":168,"h":195},
	"rotated": false,
	"trimmed": true,
	"spriteSourceSize": {"x":821,"y":821,"w":168,"h":195},
	"sourceSize": {"w":1800,"h":1800}
},
{
	"filename": "02-w-20.png",
	"frame": {"x":840,"y":1,"w":178,"h":209},
	"rotated": false,
	"trimmed": true,
	"spriteSourceSize": {"x":814,"y":817,"w":178,"h":209},
	"sourceSize": {"w":1800,"h":1800}
},
{
	"filename": "02-w-21.png",
	"frame": {"x":447,"y":1,"w":187,"h":211},
	"rotated": false,
	"trimmed": true,
	"spriteSourceSize": {"x":808,"y":812,"w":187,"h":211},
	"sourceSize": {"w":1800,"h":1800}
},
{
	"filename": "02-w-22.png",
	"frame": {"x":227,"y":187,"w":193,"h":203},
	"rotated": false,
	"trimmed": true,
	"spriteSourceSize": {"x":806,"y":809,"w":193,"h":203},
	"sourceSize": {"w":1800,"h":1800}
},
{
	"filename": "02-w-23.png",
	"frame": {"x":636,"y":1,"w":202,"h":187},
	"rotated": false,
	"trimmed": true,
	"spriteSourceSize": {"x":801,"y":806,"w":202,"h":187},
	"sourceSize": {"w":1800,"h":1800}
},
{
	"filename": "02-w-24.png",
	"frame": {"x":1,"y":192,"w":212,"h":182},
	"rotated": false,
	"trimmed": true,
	"spriteSourceSize": {"x":796,"y":802,"w":212,"h":182},
	"sourceSize": {"w":1800,"h":1800}
},
{
	"filename": "02-w-25.png",
	"frame": {"x":1,"y":1,"w":224,"h":189},
	"rotated": false,
	"trimmed": true,
	"spriteSourceSize": {"x":792,"y":800,"w":224,"h":189},
	"sourceSize": {"w":1800,"h":1800}
},
{
	"filename": "02-w-26.png",
	"frame": {"x":227,"y":1,"w":218,"h":184},
	"rotated": false,
	"trimmed": true,
	"spriteSourceSize": {"x":794,"y":803,"w":218,"h":184},
	"sourceSize": {"w":1800,"h":1800}
},
{
	"filename": "02-w-27.png",
	"frame": {"x":1,"y":376,"w":212,"h":180},
	"rotated": false,
	"trimmed": true,
	"spriteSourceSize": {"x":797,"y":805,"w":212,"h":180},
	"sourceSize": {"w":1800,"h":1800}
},
{
	"filename": "02-w-28.png",
	"frame": {"x":422,"y":214,"w":206,"h":175},
	"rotated": false,
	"trimmed": true,
	"spriteSourceSize": {"x":799,"y":808,"w":206,"h":175},
	"sourceSize": {"w":1800,"h":1800}
},
{
	"filename": "02-w-29.png",
	"frame": {"x":422,"y":391,"w":200,"h":170},
	"rotated": false,
	"trimmed": true,
	"spriteSourceSize": {"x":802,"y":810,"w":200,"h":170},
	"sourceSize": {"w":1800,"h":1800}
}],
"meta": {
	"app": "http://www.codeandweb.com/texturepacker",
	"version": "1.0",
	"image": "2.png",
	"format": "RGBA8888",
	"size": {"w":1024,"h":2048},
	"scale": "1",
	"smartupdate": "$TexturePacker:SmartUpdate:784a540e02b2059a34cee4c1fbcfd0e0:9397c6aa969f09e760b6c2219e8d6c9e:5ed6fcaeb66fa059fba7886eb3eee15a$"
}
}
