{"frames": [

{
	"filename": "05-b-00.png",
	"frame": {"x":159,"y":825,"w":119,"h":144},
	"rotated": false,
	"trimmed": true,
	"spriteSourceSize": {"x":621,"y":603,"w":119,"h":144},
	"sourceSize": {"w":1350,"h":1350}
},
{
	"filename": "05-n-00.png",
	"frame": {"x":558,"y":759,"w":120,"h":128},
	"rotated": false,
	"trimmed": true,
	"spriteSourceSize": {"x":621,"y":612,"w":120,"h":128},
	"sourceSize": {"w":1350,"h":1350}
},
{
	"filename": "05-w-00.png",
	"frame": {"x":676,"y":889,"w":120,"h":128},
	"rotated": false,
	"trimmed": true,
	"spriteSourceSize": {"x":621,"y":612,"w":120,"h":128},
	"sourceSize": {"w":1350,"h":1350}
},
{
	"filename": "05-w-01.png",
	"frame": {"x":556,"y":897,"w":118,"h":124},
	"rotated": false,
	"trimmed": true,
	"spriteSourceSize": {"x":622,"y":614,"w":118,"h":124},
	"sourceSize": {"w":1350,"h":1350}
},
{
	"filename": "05-w-02.png",
	"frame": {"x":581,"y":289,"w":118,"h":120},
	"rotated": false,
	"trimmed": true,
	"spriteSourceSize": {"x":622,"y":615,"w":118,"h":120},
	"sourceSize": {"w":1350,"h":1350}
},
{
	"filename": "05-w-03.png",
	"frame": {"x":584,"y":125,"w":116,"h":120},
	"rotated": false,
	"trimmed": true,
	"spriteSourceSize": {"x":623,"y":612,"w":116,"h":120},
	"sourceSize": {"w":1350,"h":1350}
},
{
	"filename": "05-w-04.png",
	"frame": {"x":484,"y":1,"w":116,"h":122},
	"rotated": false,
	"trimmed": true,
	"spriteSourceSize": {"x":623,"y":609,"w":116,"h":122},
	"sourceSize": {"w":1350,"h":1350}
},
{
	"filename": "05-w-05.png",
	"frame": {"x":459,"y":454,"w":114,"h":124},
	"rotated": false,
	"trimmed": true,
	"spriteSourceSize": {"x":624,"y":605,"w":114,"h":124},
	"sourceSize": {"w":1350,"h":1350}
},
{
	"filename": "05-w-06.png",
	"frame": {"x":466,"y":315,"w":113,"h":124},
	"rotated": false,
	"trimmed": true,
	"spriteSourceSize": {"x":624,"y":604,"w":113,"h":124},
	"sourceSize": {"w":1350,"h":1350}
},
{
	"filename": "05-w-07.png",
	"frame": {"x":470,"y":164,"w":112,"h":123},
	"rotated": false,
	"trimmed": true,
	"spriteSourceSize": {"x":625,"y":603,"w":112,"h":123},
	"sourceSize": {"w":1350,"h":1350}
},
{
	"filename": "05-w-08.png",
	"frame": {"x":575,"y":441,"w":118,"h":121},
	"rotated": false,
	"trimmed": true,
	"spriteSourceSize": {"x":622,"y":609,"w":118,"h":121},
	"sourceSize": {"w":1350,"h":1350}
},
{
	"filename": "05-w-09.png",
	"frame": {"x":602,"y":1,"w":123,"h":118},
	"rotated": false,
	"trimmed": true,
	"spriteSourceSize": {"x":619,"y":616,"w":123,"h":118},
	"sourceSize": {"w":1350,"h":1350}
},
{
	"filename": "05-w-10.png",
	"frame": {"x":425,"y":897,"w":129,"h":125},
	"rotated": false,
	"trimmed": true,
	"spriteSourceSize": {"x":616,"y":612,"w":129,"h":125},
	"sourceSize": {"w":1350,"h":1350}
},
{
	"filename": "05-w-11.png",
	"frame": {"x":317,"y":627,"w":134,"h":133},
	"rotated": false,
	"trimmed": true,
	"spriteSourceSize": {"x":614,"y":608,"w":134,"h":133},
	"sourceSize": {"w":1350,"h":1350}
},
{
	"filename": "05-w-12.png",
	"frame": {"x":317,"y":484,"w":140,"h":141},
	"rotated": false,
	"trimmed": true,
	"spriteSourceSize": {"x":611,"y":605,"w":140,"h":141},
	"sourceSize": {"w":1350,"h":1350}
},
{
	"filename": "05-w-13.png",
	"frame": {"x":324,"y":164,"w":144,"h":149},
	"rotated": false,
	"trimmed": true,
	"spriteSourceSize": {"x":609,"y":601,"w":144,"h":149},
	"sourceSize": {"w":1350,"h":1350}
},
{
	"filename": "05-w-14.png",
	"frame": {"x":1,"y":504,"w":150,"h":159},
	"rotated": false,
	"trimmed": true,
	"spriteSourceSize": {"x":606,"y":597,"w":150,"h":159},
	"sourceSize": {"w":1350,"h":1350}
},
{
	"filename": "05-w-15.png",
	"frame": {"x":1,"y":1,"w":156,"h":167},
	"rotated": false,
	"trimmed": true,
	"spriteSourceSize": {"x":602,"y":593,"w":156,"h":167},
	"sourceSize": {"w":1350,"h":1350}
},
{
	"filename": "05-w-16.png",
	"frame": {"x":1,"y":170,"w":157,"h":166},
	"rotated": false,
	"trimmed": true,
	"spriteSourceSize": {"x":601,"y":593,"w":157,"h":166},
	"sourceSize": {"w":1350,"h":1350}
},
{
	"filename": "05-w-17.png",
	"frame": {"x":159,"y":1,"w":158,"h":165},
	"rotated": false,
	"trimmed": true,
	"spriteSourceSize": {"x":600,"y":594,"w":158,"h":165},
	"sourceSize": {"w":1350,"h":1350}
},
{
	"filename": "05-w-18.png",
	"frame": {"x":1,"y":338,"w":160,"h":164},
	"rotated": false,
	"trimmed": true,
	"spriteSourceSize": {"x":599,"y":594,"w":160,"h":164},
	"sourceSize": {"w":1350,"h":1350}
},
{
	"filename": "05-w-19.png",
	"frame": {"x":160,"y":168,"w":162,"h":162},
	"rotated": false,
	"trimmed": true,
	"spriteSourceSize": {"x":598,"y":595,"w":162,"h":162},
	"sourceSize": {"w":1350,"h":1350}
},
{
	"filename": "05-w-20.png",
	"frame": {"x":319,"y":1,"w":163,"h":161},
	"rotated": false,
	"trimmed": true,
	"spriteSourceSize": {"x":597,"y":595,"w":163,"h":161},
	"sourceSize": {"w":1350,"h":1350}
},
{
	"filename": "05-w-21.png",
	"frame": {"x":1,"y":665,"w":163,"h":158},
	"rotated": false,
	"trimmed": true,
	"spriteSourceSize": {"x":597,"y":597,"w":163,"h":158},
	"sourceSize": {"w":1350,"h":1350}
},
{
	"filename": "05-w-22.png",
	"frame": {"x":153,"y":504,"w":162,"h":154},
	"rotated": false,
	"trimmed": true,
	"spriteSourceSize": {"x":598,"y":599,"w":162,"h":154},
	"sourceSize": {"w":1350,"h":1350}
},
{
	"filename": "05-w-23.png",
	"frame": {"x":163,"y":332,"w":162,"h":150},
	"rotated": false,
	"trimmed": true,
	"spriteSourceSize": {"x":598,"y":601,"w":162,"h":150},
	"sourceSize": {"w":1350,"h":1350}
},
{
	"filename": "05-w-24.png",
	"frame": {"x":1,"y":825,"w":156,"h":148},
	"rotated": false,
	"trimmed": true,
	"spriteSourceSize": {"x":601,"y":602,"w":156,"h":148},
	"sourceSize": {"w":1350,"h":1350}
},
{
	"filename": "05-w-25.png",
	"frame": {"x":166,"y":660,"w":149,"h":143},
	"rotated": false,
	"trimmed": true,
	"spriteSourceSize": {"x":605,"y":605,"w":149,"h":143},
	"sourceSize": {"w":1350,"h":1350}
},
{
	"filename": "05-w-26.png",
	"frame": {"x":280,"y":805,"w":143,"h":141},
	"rotated": false,
	"trimmed": true,
	"spriteSourceSize": {"x":608,"y":606,"w":143,"h":141},
	"sourceSize": {"w":1350,"h":1350}
},
{
	"filename": "05-w-27.png",
	"frame": {"x":327,"y":315,"w":137,"h":137},
	"rotated": false,
	"trimmed": true,
	"spriteSourceSize": {"x":611,"y":608,"w":137,"h":137},
	"sourceSize": {"w":1350,"h":1350}
},
{
	"filename": "05-w-28.png",
	"frame": {"x":425,"y":762,"w":131,"h":133},
	"rotated": false,
	"trimmed": true,
	"spriteSourceSize": {"x":615,"y":610,"w":131,"h":133},
	"sourceSize": {"w":1350,"h":1350}
},
{
	"filename": "05-w-29.png",
	"frame": {"x":453,"y":627,"w":125,"h":130},
	"rotated": false,
	"trimmed": true,
	"spriteSourceSize": {"x":618,"y":611,"w":125,"h":130},
	"sourceSize": {"w":1350,"h":1350}
}],
"meta": {
	"app": "http://www.codeandweb.com/texturepacker",
	"version": "1.0",
	"image": "5.png",
	"format": "RGBA8888",
	"size": {"w":1024,"h":1024},
	"scale": "0.75",
	"smartupdate": "$TexturePacker:SmartUpdate:824d584e886a8db30265cafa108f6ee4:072e3968a820c731c08dca8530e007f8:9addbf21a64760fa23b46a82ab6e4587$"
}
}
